kblpbyp2/__init__.py
kblpbyp2/webscrape.py
kblpbyp2-0.0.6.dist-info/METADATA
kblpbyp2-0.0.6.dist-info/WHEEL
kblpbyp2-0.0.6.dist-info/top_level.txt
kblpbyp2-0.0.6.dist-info/RECORD
